mlchecks/__init__.py
deepchecks_server-0.0.1.dist-info/METADATA
deepchecks_server-0.0.1.dist-info/WHEEL
deepchecks_server-0.0.1.dist-info/top_level.txt
deepchecks_server-0.0.1.dist-info/RECORD
