Metadata-Version: 2.1
Name: deepchecks-server
Version: 0.0.1
Summary: Package for validating your machine learning model and data
Home-page: https://github.com/deepchecks/MLChecks
Author: deepchecks
Author-email: info@deepchecks.com
License: UNKNOWN
Download-URL: https://github.com/deepchecks/MLChecks/releases/download/0.0.1/mlchecks-0.0.1.tar.gz
Keywords: Software Development,Machine Learning
Platform: UNKNOWN
Classifier: Intended Audience :: Developers
Classifier: Intended Audience :: Science/Research
Classifier: Topic :: Software Development
Classifier: Topic :: Scientific/Engineering
Classifier: License :: OSI Approved :: BSD License
Classifier: Programming Language :: Python :: 3
Classifier: Programming Language :: Python :: 3.6
Classifier: Programming Language :: Python :: 3.7
Classifier: Programming Language :: Python :: 3.8
Classifier: Programming Language :: Python :: 3.9
Classifier: Programming Language :: Python :: 3.10
